powar/__init__.py
powar/global_config.py
powar/main.py
powar/module_config.py
powar/settings.py
powar/util.py
powar-1.0.3.dist-info/LICENSE
powar-1.0.3.dist-info/METADATA
powar-1.0.3.dist-info/WHEEL
powar-1.0.3.dist-info/entry_points.txt
powar-1.0.3.dist-info/top_level.txt
powar-1.0.3.dist-info/RECORD
